stemre/__init__.py
stemre/calculus.py
stemre/initial_value_problems.py
stemre/base/__init__.py
stemre/base/default.py
stemre/business_finance/__init__.py
stemre/business_finance/time_value_of_money/__init__.py
stemre/business_finance/time_value_of_money/base.py
stemre/mathematics/__init__.py
stemre/mathematics/calculus/__init__.py
stemre/mathematics/calculus/differentiation.py
stemre/mathematics/calculus/integration.py
stemre/mathematics/calculus/numerical_differentiation.py
stemre/mathematics/calculus/numerical_integration.py
stemre/mathematics/calculus/univariate_interpolation.py
stemre/mathematics/calculus/vector_differential_calculus.py
stemre/mathematics/calculus/vector_integral_calculus.py
stemre/mathematics/interpolation/__init__.py
stemre/mathematics/interpolation/lagrange_interpolation.py
stemre/mathematics/interpolation/linear_interpolation.py
stemre/mathematics/interpolation/newton_differences.py
stemre/mathematics/linear_algebra/__init__.py
stemre/mathematics/linear_algebra/base.py
stemre/mathematics/linear_algebra/direct_solutions.py
stemre/mathematics/linear_algebra/iterative_solutions.py
stemre/mathematics/linear_algebra/matrices.py
stemre/mathematics/linear_algebra/matrix_arithmetics.py
stemre/mathematics/ode/__init__.py
stemre/mathematics/ode/initial_value_problems.py
stemre/mathematics/ode/ivp.py
stemre/mathematics/pre_calculus/__init__.py
stemre/mathematics/pre_calculus/base.py
stemre/statistics/__init__.py
stemre/statistics/descriptive_statistics/__init__.py
stemre/statistics/descriptive_statistics/base.py
stemre-0.0.17.dist-info/LICENSE.txt
stemre-0.0.17.dist-info/METADATA
stemre-0.0.17.dist-info/WHEEL
stemre-0.0.17.dist-info/top_level.txt
stemre-0.0.17.dist-info/RECORD
