Metadata-Version: 2.1
Name: stemre
Version: 0.0.17
Summary: Numerical analysis, simulation and data fitting in STEM
Home-page: https://github.com/StemResearch/stemre
Author: Stem Research
Author-email: stemresearchs@gmail.com
License: UNKNOWN
Platform: UNKNOWN
Classifier: Programming Language :: Python :: 3
Classifier: License :: OSI Approved :: MIT License
Classifier: Operating System :: OS Independent
Requires-Python: >=3.6
